biomedicus_client/__init__.py
biomedicus_client/__main__.py
biomedicus_client/_run.py
biomedicus_client/cli.py
biomedicus_client/default_pipeline.py
biomedicus_client/rtf_to_text.py
biomedicus_client/sources.py
biomedicus_client/version.py
biomedicus_client/cli_tools/__init__.py
biomedicus_client/cli_tools/command.py
biomedicus_client/cli_tools/config_writing.py
biomedicus_client/cli_tools/parser.py
biomedicus_client/pipeline_confs/__init__.py
biomedicus_client/pipeline_confs/biomedicus_default_pipeline.yml
biomedicus_client/pipeline_confs/rtf_to_text_pipeline.yml
biomedicus_client/pipeline_confs/scaleout_pipeline.yml
biomedicus_client-3.4.3.dist-info/LICENSE.txt
biomedicus_client-3.4.3.dist-info/METADATA
biomedicus_client-3.4.3.dist-info/WHEEL
biomedicus_client-3.4.3.dist-info/entry_points.txt
biomedicus_client-3.4.3.dist-info/top_level.txt
biomedicus_client-3.4.3.dist-info/RECORD
